MANIFEST.in
README.txt
setup.cfg
setup.py
collective/__init__.py
collective.zipfiletransport.egg-info/PKG-INFO
collective.zipfiletransport.egg-info/SOURCES.txt
collective.zipfiletransport.egg-info/dependency_links.txt
collective.zipfiletransport.egg-info/entry_points.txt
collective.zipfiletransport.egg-info/namespace_packages.txt
collective.zipfiletransport.egg-info/not-zip-safe
collective.zipfiletransport.egg-info/requires.txt
collective.zipfiletransport.egg-info/top_level.txt
collective/zipfiletransport/INSTALL.txt
collective/zipfiletransport/LICENSE.GPL
collective/zipfiletransport/LICENSE.ZPL
collective/zipfiletransport/LICENSE.txt
collective/zipfiletransport/README.txt
collective/zipfiletransport/__init__.py
collective/zipfiletransport/config.py
collective/zipfiletransport/configure.zcml
collective/zipfiletransport/interfaces.py
collective/zipfiletransport/refresh.txt
collective/zipfiletransport/schemas.py
collective/zipfiletransport/tool.gif
collective/zipfiletransport/version.txt
collective/zipfiletransport/Extensions/__init__.py
collective/zipfiletransport/browser/__init__.py
collective/zipfiletransport/browser/configure.zcml
collective/zipfiletransport/browser/export_widget.pt
collective/zipfiletransport/browser/interfaces.py
collective/zipfiletransport/browser/widgets.py
collective/zipfiletransport/browser/zipexport.py
collective/zipfiletransport/browser/zipfiletransportprefs.py
collective/zipfiletransport/browser/zipimport.py
collective/zipfiletransport/i18n/plone-af.po
collective/zipfiletransport/i18n/plone-ar.po
collective/zipfiletransport/i18n/plone-bn.po
collective/zipfiletransport/i18n/plone-ca.po
collective/zipfiletransport/i18n/plone-de.po
collective/zipfiletransport/i18n/plone-en.po
collective/zipfiletransport/i18n/plone-es.po
collective/zipfiletransport/i18n/plone-fr.po
collective/zipfiletransport/i18n/plone-hi.po
collective/zipfiletransport/i18n/plone-hu.po
collective/zipfiletransport/i18n/plone-it.po
collective/zipfiletransport/i18n/plone-ja.po
collective/zipfiletransport/i18n/plone-ko.po
collective/zipfiletransport/i18n/plone-ne.po
collective/zipfiletransport/i18n/plone-nl.po
collective/zipfiletransport/i18n/plone-pt-br.po
collective/zipfiletransport/i18n/plone-pt.po
collective/zipfiletransport/i18n/plone-ru.po
collective/zipfiletransport/i18n/plone-tr.po
collective/zipfiletransport/i18n/plone-vi.po
collective/zipfiletransport/i18n/plone-zh-cn.po
