Metadata-Version: 1.1
Name: collective.zipfiletransport
Version: 3.2.3
Summary: This tool is used to import and export zip files.
Home-page: http://plone.org/products/collective.zipfiletransport
Author: enPraxis
Author-email: info@enpraxis.net
License: GPL
Keywords: zipfile bulk upload
Platform: UNKNOWN
Classifier: Framework :: Plone
Classifier: Programming Language :: Python
Classifier: Topic :: Software Development :: Libraries :: Python Modules
